package/__init__.py
package/piunit.py
package/test.py
piunit/__init__.py
piunit/test.py
PIUnit-1.0.5.dist-info/LICENSE
PIUnit-1.0.5.dist-info/METADATA
PIUnit-1.0.5.dist-info/WHEEL
PIUnit-1.0.5.dist-info/top_level.txt
PIUnit-1.0.5.dist-info/RECORD
