Metadata-Version: 2.1
Name: PIUnit
Version: 1.0.5
Summary: Library for convenient code testing with print and input functions
Home-page: https://github.com/Ryize/PIUnit
Author: MChekashov
Author-email: chekashovmatvey@gmail.com
Project-URL: Documentation, https://github.com/Ryize/PIUnit
Keywords: python test unittest print input
Classifier: Programming Language :: Python :: 3.9
Requires-Python: >=3.7
License-File: LICENSE
